{
  "mdVersion": [
    "1.3"
  ],
  "txid": "2d69051926ef0c064be504293fa45f395be79e0f13e2a7512b4afc3016d3a4ec",
  "msg": [
    "Singularity-Net Transaction",
    "Ideascale: ",
    "Recipients: 1",
    "0.48 USD in 1.344798 ADA",
    "0 USD in 200000.00 GovWG",
    "Transaction made by Treasury Guild @0.355",
    "https://www.treasuryguild.io/"
  ],
  "contributions": [
    {
      "taskCreator": "Singularity-Net",
      "label": "Incoming",
      "description": [
        "Incoming of 200000 GovWG tokens from Snet Ambassador",
        "Governance Workgroup"
      ],
      "contributors": {
        "Snet Ambassador Gov ": {
          "ADA": "1.344798",
          "GovWG": "200000"
        }
      }
    }
  ]
}
